[
    {
        "_id": "6481db2f77f0a16116c691a2",
        "user_name": "相璇國",
        "user_email": "Mikayla_Witting91@yahoo.com",
        "user_hash_pwd": "$2a$12$6L2LRYRx5PYlxi5Hy2B.BeXet.D5PNJ5pcw5SyKdrh2pNQE4kUXWS",
        "user_roles": [
            0,
            2
        ],
        "login_method": [
            0
        ],
        "oauth_google_id": "",
        "user_create_date": "2022-09-21T08:10:47.309Z",
        "user_update_date": "2023-04-30T11:49:18.609Z",
        "user_cover": "cover URL",
        "user_phone": "0932140342",
        "user_intro": "user intro",
        "user_website": "website",
        "user_interests": [],
        "user_like": []
    },
    {
        "_id": "6481db2f77f0a16116c691a3",
        "user_name": "通婉達",
        "user_email": "Andres.Koch-Russel79@yahoo.com",
        "user_hash_pwd": "$2a$12$gG7mQmASaPeBYZHl.3B.Ru0J3GP9SRRFUaTHOFDHLCezuPZiJMNs2",
        "user_roles": [
            0,
            2
        ],
        "login_method": [
            0
        ],
        "oauth_google_id": "",
        "user_create_date": "2021-03-17T20:01:42.950Z",
        "user_update_date": "2023-05-11T23:23:39.870Z",
        "user_cover": "cover URL",
        "user_phone": "0934638418",
        "user_intro": "user intro",
        "user_website": "website",
        "user_interests": [],
        "user_like": []
    },
    {
        "_id": "6481db2f77f0a16116c691a4",
        "user_name": "單於千芳",
        "user_email": "Jamar.Kulas@yahoo.com",
        "user_hash_pwd": "$2a$12$172smWTAGBVb3IZdrgKbeexaVuxzW9HEXiLf6Iv05JA3Oxu8oGO06",
        "user_roles": [
            0,
            2
        ],
        "login_method": [
            0
        ],
        "oauth_google_id": "",
        "user_create_date": "2020-01-07T09:15:43.559Z",
        "user_update_date": "2023-04-24T11:01:44.550Z",
        "user_cover": "cover URL",
        "user_phone": "0925084276",
        "user_intro": "user intro",
        "user_website": "website",
        "user_interests": [],
        "user_like": []
    },
    {
        "_id": "6481db2f77f0a16116c691a5",
        "user_name": "邱福儒",
        "user_email": "Thea.Kassulke@yahoo.com",
        "user_hash_pwd": "$2a$12$igkQFrl8abVOdWg5Amgf7.I9sbd1mT4QO2FZKA/VCMBnK2PTWRfUi",
        "user_roles": [
            0,
            2
        ],
        "login_method": [
            0
        ],
        "oauth_google_id": "",
        "user_create_date": "2020-11-28T14:33:57.609Z",
        "user_update_date": "2023-04-05T00:32:26.771Z",
        "user_cover": "cover URL",
        "user_phone": "0934885572",
        "user_intro": "user intro",
        "user_website": "website",
        "user_interests": [],
        "user_like": []
    },
    {
        "_id": "6481db2f77f0a16116c691a6",
        "user_name": "黎菁明",
        "user_email": "Haven82@hotmail.com",
        "user_hash_pwd": "$2a$12$qRB3LbUzk.xSaXglArp5/e5tZsQKYPypc0JskwX1d0nzdv94FRLDO",
        "user_roles": [
            0,
            2
        ],
        "login_method": [
            0
        ],
        "oauth_google_id": "",
        "user_create_date": "2020-04-18T03:27:02.867Z",
        "user_update_date": "2023-05-15T07:07:49.419Z",
        "user_cover": "cover URL",
        "user_phone": "0922815743",
        "user_intro": "user intro",
        "user_website": "website",
        "user_interests": [],
        "user_like": []
    },
    {
        "_id": "6481db2f77f0a16116c691a7",
        "user_name": "豐國宗",
        "user_email": "Kathleen_Abshire62@hotmail.com",
        "user_hash_pwd": "$2a$12$mz4YIQl5Z5HxONQ2pVIR5e6LOKRUKn0P8tmCWNa5M0IZDSg7WGhJq",
        "user_roles": [
            0,
            2
        ],
        "login_method": [
            0
        ],
        "oauth_google_id": "",
        "user_create_date": "2021-03-18T08:18:05.136Z",
        "user_update_date": "2023-04-05T06:13:00.605Z",
        "user_cover": "cover URL",
        "user_phone": "0935164781",
        "user_intro": "user intro",
        "user_website": "website",
        "user_interests": [],
        "user_like": []
    },
    {
        "_id": "6481db2f77f0a16116c691a8",
        "user_name": "戴霖學",
        "user_email": "Edmund_Ernser@gmail.com",
        "user_hash_pwd": "$2a$12$pCjMhWcTOetyzz6Bjx.DYO.DjboxC07P8jUS6VFueQWZagzqO13ES",
        "user_roles": [
            0,
            2
        ],
        "login_method": [
            0
        ],
        "oauth_google_id": "",
        "user_create_date": "2020-07-03T20:09:48.457Z",
        "user_update_date": "2023-04-02T04:55:40.721Z",
        "user_cover": "cover URL",
        "user_phone": "0963242536",
        "user_intro": "user intro",
        "user_website": "website",
        "user_interests": [],
        "user_like": []
    },
    {
        "_id": "6481db2f77f0a16116c691a9",
        "user_name": "景若琳",
        "user_email": "Julius.Larson@hotmail.com",
        "user_hash_pwd": "$2a$12$wZnI0GiVZTiF/SEsw/.rTe3OulnZxfcz0vdzflYCQaOvsKRI3YmF2",
        "user_roles": [
            0,
            2
        ],
        "login_method": [
            0
        ],
        "oauth_google_id": "",
        "user_create_date": "2022-11-17T00:23:34.125Z",
        "user_update_date": "2023-04-29T15:01:56.569Z",
        "user_cover": "cover URL",
        "user_phone": "0982663501",
        "user_intro": "user intro",
        "user_website": "website",
        "user_interests": [],
        "user_like": []
    },
    {
        "_id": "6481db2f77f0a16116c691aa",
        "user_name": "林翰彥",
        "user_email": "Josie.Altenwerth70@gmail.com",
        "user_hash_pwd": "$2a$12$EKvUqQEHVIAYpf8QOxzyQuKQY9TC9JgQ8wFJnqJGU6SV67YK7oLK2",
        "user_roles": [
            0,
            2
        ],
        "login_method": [
            0
        ],
        "oauth_google_id": "",
        "user_create_date": "2020-10-29T18:23:28.450Z",
        "user_update_date": "2023-05-16T03:52:06.038Z",
        "user_cover": "cover URL",
        "user_phone": "0963157174",
        "user_intro": "user intro",
        "user_website": "website",
        "user_interests": [],
        "user_like": []
    },
    {
        "_id": "6481db2f77f0a16116c691ab",
        "user_name": "江文宇",
        "user_email": "Joesph_Sporer-Balistreri43@gmail.com",
        "user_hash_pwd": "$2a$12$zXM08LTEUZLylV0xGZI1keoOPfLS2OfGK1tq3ex1Y9UldpaEy0FOG",
        "user_roles": [
            0,
            2
        ],
        "login_method": [
            0
        ],
        "oauth_google_id": "",
        "user_create_date": "2020-12-14T15:34:46.965Z",
        "user_update_date": "2023-04-09T20:43:05.763Z",
        "user_cover": "cover URL",
        "user_phone": "0923600622",
        "user_intro": "user intro",
        "user_website": "website",
        "user_interests": [],
        "user_like": []
    },
    {
        "_id": "6481db2f77f0a16116c691ac",
        "user_name": "蔡峰柄",
        "user_email": "Alexa_Heidenreich@hotmail.com",
        "user_hash_pwd": "$2a$12$MM6LBTP4WSPbXeC7SVXCTO.a160DdO4apa2u3YyNcPd/hjl9w9.ma",
        "user_roles": [
            0,
            2
        ],
        "login_method": [
            0
        ],
        "oauth_google_id": "",
        "user_create_date": "2021-11-24T09:56:03.310Z",
        "user_update_date": "2023-04-27T15:18:19.729Z",
        "user_cover": "cover URL",
        "user_phone": "0986100683",
        "user_intro": "user intro",
        "user_website": "website",
        "user_interests": [],
        "user_like": []
    },
    {
        "_id": "6481db2f77f0a16116c691ad",
        "user_name": "錢洲稜",
        "user_email": "Domenick80@gmail.com",
        "user_hash_pwd": "$2a$12$jSgvT265kNlXyZpkwMOpluEE0MhDDBpaaSljd49l7a4tzO6OcbYjK",
        "user_roles": [
            0,
            2
        ],
        "login_method": [
            0
        ],
        "oauth_google_id": "",
        "user_create_date": "2022-02-01T05:37:16.267Z",
        "user_update_date": "2023-05-21T03:14:47.069Z",
        "user_cover": "cover URL",
        "user_phone": "0930334564",
        "user_intro": "user intro",
        "user_website": "website",
        "user_interests": [],
        "user_like": []
    },
    {
        "_id": "6481db2f77f0a16116c691ae",
        "user_name": "鄭華乃",
        "user_email": "Wilma39@yahoo.com",
        "user_hash_pwd": "$2a$12$Z6gIFybAYqw7q/hczKB2He/ZOp8KiyJfNrQWeHdPIKEZ4/wUDSfvi",
        "user_roles": [
            0,
            2
        ],
        "login_method": [
            0
        ],
        "oauth_google_id": "",
        "user_create_date": "2021-04-03T07:53:12.624Z",
        "user_update_date": "2023-05-14T15:16:12.899Z",
        "user_cover": "cover URL",
        "user_phone": "0931005246",
        "user_intro": "user intro",
        "user_website": "website",
        "user_interests": [],
        "user_like": []
    },
    {
        "_id": "6481db2f77f0a16116c691af",
        "user_name": "梁伶薇",
        "user_email": "Tanya45@gmail.com",
        "user_hash_pwd": "$2a$12$PV08igPJFl6xG/OY20BgG.uirGPzsHgAr76GYzlvfMWV./KJ23rb.",
        "user_roles": [
            0,
            2
        ],
        "login_method": [
            0
        ],
        "oauth_google_id": "",
        "user_create_date": "2021-08-02T16:48:11.371Z",
        "user_update_date": "2023-04-10T19:31:31.857Z",
        "user_cover": "cover URL",
        "user_phone": "0986785501",
        "user_intro": "user intro",
        "user_website": "website",
        "user_interests": [],
        "user_like": []
    },
    {
        "_id": "6481db2f77f0a16116c691b0",
        "user_name": "柳元漢",
        "user_email": "Violette.Rogahn@hotmail.com",
        "user_hash_pwd": "$2a$12$7AXLmhFcWmkiCEUch37v3OHjSwDLq5aZB/XryHrhO3YWi32hFPnSm",
        "user_roles": [
            0,
            2
        ],
        "login_method": [
            0
        ],
        "oauth_google_id": "",
        "user_create_date": "2020-07-24T19:08:11.106Z",
        "user_update_date": "2023-05-07T10:10:17.130Z",
        "user_cover": "cover URL",
        "user_phone": "0963860121",
        "user_intro": "user intro",
        "user_website": "website",
        "user_interests": [],
        "user_like": []
    },
    {
        "_id": "6481db2f77f0a16116c691b1",
        "user_name": "陶婷太",
        "user_email": "Verdie_Kuhlman50@gmail.com",
        "user_hash_pwd": "$2a$12$QEjYw6XKiQUvdiqhyMkrTO5B8CcA4oW6YZojPwF2hoFK7y6kaUnBS",
        "user_roles": [
            0,
            2
        ],
        "login_method": [
            0
        ],
        "oauth_google_id": "",
        "user_create_date": "2021-06-26T02:59:50.210Z",
        "user_update_date": "2023-04-15T20:23:25.213Z",
        "user_cover": "cover URL",
        "user_phone": "0920481510",
        "user_intro": "user intro",
        "user_website": "website",
        "user_interests": [],
        "user_like": []
    },
    {
        "_id": "6481db2f77f0a16116c691b2",
        "user_name": "龍振豪",
        "user_email": "Sophia_Barton68@hotmail.com",
        "user_hash_pwd": "$2a$12$eReH15tkFQMf7IOsC5tTT.2tmDcQVqIGVAg/wXsWziUIdeLAZudgq",
        "user_roles": [
            0,
            2
        ],
        "login_method": [
            0
        ],
        "oauth_google_id": "",
        "user_create_date": "2021-08-16T17:07:56.902Z",
        "user_update_date": "2023-05-21T01:23:12.718Z",
        "user_cover": "cover URL",
        "user_phone": "0937128775",
        "user_intro": "user intro",
        "user_website": "website",
        "user_interests": [],
        "user_like": []
    },
    {
        "_id": "6481db2f77f0a16116c691b3",
        "user_name": "梁傑南",
        "user_email": "Alfreda3@hotmail.com",
        "user_hash_pwd": "$2a$12$FIJn7xKUbPTyBLpT43pxKueXfwUMoMoZJZuANrZ2Az30NdpeXdp6.",
        "user_roles": [
            0,
            2
        ],
        "login_method": [
            0
        ],
        "oauth_google_id": "",
        "user_create_date": "2022-05-22T02:20:27.843Z",
        "user_update_date": "2023-05-18T17:04:49.943Z",
        "user_cover": "cover URL",
        "user_phone": "0922461078",
        "user_intro": "user intro",
        "user_website": "website",
        "user_interests": [],
        "user_like": []
    },
    {
        "_id": "6481db2f77f0a16116c691b4",
        "user_name": "桂庭謙",
        "user_email": "Lindsey_Emmerich-Koch32@yahoo.com",
        "user_hash_pwd": "$2a$12$HJyQOTM0rN43dYrsykhWHOCzjD1V47D/f3uRB1DIzm7kr5KqlWQrC",
        "user_roles": [
            0,
            2
        ],
        "login_method": [
            0
        ],
        "oauth_google_id": "",
        "user_create_date": "2020-04-11T18:08:55.248Z",
        "user_update_date": "2023-04-26T19:15:39.311Z",
        "user_cover": "cover URL",
        "user_phone": "0937338773",
        "user_intro": "user intro",
        "user_website": "website",
        "user_interests": [],
        "user_like": []
    },
    {
        "_id": "6481db2f77f0a16116c691b5",
        "user_name": "鄭建澤",
        "user_email": "Coby_Koelpin12@hotmail.com",
        "user_hash_pwd": "$2a$12$ES616BpRq1qQOsBJQKyJv.6J.V.pJor0I6IBWu3jEeHn8d29ECLcO",
        "user_roles": [
            0,
            2
        ],
        "login_method": [
            0
        ],
        "oauth_google_id": "",
        "user_create_date": "2020-09-15T08:50:04.100Z",
        "user_update_date": "2023-04-27T15:13:39.484Z",
        "user_cover": "cover URL",
        "user_phone": "0919382816",
        "user_intro": "user intro",
        "user_website": "website",
        "user_interests": [],
        "user_like": []
    },
    {
        "_id": "6481db2f77f0a16116c691b6",
        "user_name": "簡勳真",
        "user_email": "Molly92@yahoo.com",
        "user_hash_pwd": "$2a$12$85iLM/bWhEoBTHx23FAXseC9DG/6QX/tB/jGTS0t7b1za6Oi6hQrS",
        "user_roles": [
            0
        ],
        "login_method": [
            0
        ],
        "oauth_google_id": "",
        "user_create_date": "2022-04-29T17:40:15.387Z",
        "user_update_date": "2023-04-06T13:39:33.816Z",
        "user_cover": "cover URL",
        "user_phone": "0939407003",
        "user_intro": "user intro",
        "user_website": "website",
        "user_interests": [],
        "user_like": []
    },
    {
        "_id": "6481db2f77f0a16116c691b7",
        "user_name": "郭威媛",
        "user_email": "Kevon_Cormier41@gmail.com",
        "user_hash_pwd": "$2a$12$Cyc6DauPgWVnFHHY44WJzetqZRqTgmqK6ISRJu7.p/dsQ9t61AlnO",
        "user_roles": [
            0
        ],
        "login_method": [
            0
        ],
        "oauth_google_id": "",
        "user_create_date": "2021-01-02T10:38:41.415Z",
        "user_update_date": "2023-04-29T04:19:19.762Z",
        "user_cover": "cover URL",
        "user_phone": "0958746357",
        "user_intro": "user intro",
        "user_website": "website",
        "user_interests": [],
        "user_like": []
    },
    {
        "_id": "6481db2f77f0a16116c691b8",
        "user_name": "易毓豪",
        "user_email": "Adriana19@yahoo.com",
        "user_hash_pwd": "$2a$12$JFPd9KTnF07TJ.EPDbIXGeI9LW05wOTRoO66Vh4AiaOna5eG097uC",
        "user_roles": [
            0
        ],
        "login_method": [
            0
        ],
        "oauth_google_id": "",
        "user_create_date": "2022-04-14T16:26:10.090Z",
        "user_update_date": "2023-04-15T16:37:06.349Z",
        "user_cover": "cover URL",
        "user_phone": "0956254258",
        "user_intro": "user intro",
        "user_website": "website",
        "user_interests": [],
        "user_like": []
    },
    {
        "_id": "6481db2f77f0a16116c691b9",
        "user_name": "長孫玲昇",
        "user_email": "Janice.Schultz@yahoo.com",
        "user_hash_pwd": "$2a$12$jUaUdyszeLbKVHuGTb6IH.Wr3bXzdNKAA56mOoSxpuAG.NeTDk0nq",
        "user_roles": [
            0
        ],
        "login_method": [
            0
        ],
        "oauth_google_id": "",
        "user_create_date": "2022-07-12T07:22:26.319Z",
        "user_update_date": "2023-04-14T21:22:00.716Z",
        "user_cover": "cover URL",
        "user_phone": "0961058508",
        "user_intro": "user intro",
        "user_website": "website",
        "user_interests": [],
        "user_like": []
    },
    {
        "_id": "6481db2f77f0a16116c691ba",
        "user_name": "羅婉",
        "user_email": "Javier.Block88@hotmail.com",
        "user_hash_pwd": "$2a$12$X.t9BXlnvenyV2bFpescnez0OIi3ftyaV84W0UWPeK.3WwuxjkZhm",
        "user_roles": [
            0
        ],
        "login_method": [
            0
        ],
        "oauth_google_id": "",
        "user_create_date": "2020-07-02T18:32:46.169Z",
        "user_update_date": "2023-05-07T17:40:58.436Z",
        "user_cover": "cover URL",
        "user_phone": "0958165350",
        "user_intro": "user intro",
        "user_website": "website",
        "user_interests": [],
        "user_like": []
    },
    {
        "_id": "6481db2f77f0a16116c691bb",
        "user_name": "弓盈蓉",
        "user_email": "Reyes_Daniel61@yahoo.com",
        "user_hash_pwd": "$2a$12$uBHar73DzVuG0LeTc.6.e.ansj1R35.S/1P.p.m41VLn6oMSrQLDq",
        "user_roles": [
            0
        ],
        "login_method": [
            0
        ],
        "oauth_google_id": "",
        "user_create_date": "2021-03-31T18:51:31.411Z",
        "user_update_date": "2023-05-05T12:02:59.727Z",
        "user_cover": "cover URL",
        "user_phone": "0915583166",
        "user_intro": "user intro",
        "user_website": "website",
        "user_interests": [],
        "user_like": []
    },
    {
        "_id": "6481db2f77f0a16116c691bc",
        "user_name": "鍾思",
        "user_email": "Kristina_Romaguera78@hotmail.com",
        "user_hash_pwd": "$2a$12$iN6twNhKAeL6N6B/EHaRwumlm3c03ZzNNgw8SeD4GhPGFX3mlF1kC",
        "user_roles": [
            0
        ],
        "login_method": [
            0
        ],
        "oauth_google_id": "",
        "user_create_date": "2022-02-17T12:46:45.963Z",
        "user_update_date": "2023-05-12T14:22:59.785Z",
        "user_cover": "cover URL",
        "user_phone": "0921771342",
        "user_intro": "user intro",
        "user_website": "website",
        "user_interests": [],
        "user_like": []
    },
    {
        "_id": "6481db2f77f0a16116c691bd",
        "user_name": "蕭暘剛",
        "user_email": "Abner_Marquardt@hotmail.com",
        "user_hash_pwd": "$2a$12$7gGD1Qx/khpTqqYTPphwjeYm9r9YmUCwRK9i9VjpzqQXVZTxyWBb2",
        "user_roles": [
            0
        ],
        "login_method": [
            0
        ],
        "oauth_google_id": "",
        "user_create_date": "2022-10-18T00:59:48.639Z",
        "user_update_date": "2023-05-15T21:54:42.521Z",
        "user_cover": "cover URL",
        "user_phone": "0988688077",
        "user_intro": "user intro",
        "user_website": "website",
        "user_interests": [],
        "user_like": []
    },
    {
        "_id": "6481db2f77f0a16116c691be",
        "user_name": "王仕守",
        "user_email": "Mario_Stoltenberg34@hotmail.com",
        "user_hash_pwd": "$2a$12$Kn1bEYbzuc2xK1N0kgjrOeQNKJVgn0fWESibGVezMKOVJDKSo29yS",
        "user_roles": [
            0
        ],
        "login_method": [
            0
        ],
        "oauth_google_id": "",
        "user_create_date": "2021-04-02T10:39:44.729Z",
        "user_update_date": "2023-04-27T05:24:43.329Z",
        "user_cover": "cover URL",
        "user_phone": "0982667182",
        "user_intro": "user intro",
        "user_website": "website",
        "user_interests": [],
        "user_like": []
    },
    {
        "_id": "6481db2f77f0a16116c691bf",
        "user_name": "宋婷少",
        "user_email": "Polly_Corkery@hotmail.com",
        "user_hash_pwd": "$2a$12$WQU7xi4uF4UZHNf520IyjuUwaxJKDNoEHgjgD3iqmJiT43394VMBW",
        "user_roles": [
            0
        ],
        "login_method": [
            0
        ],
        "oauth_google_id": "",
        "user_create_date": "2022-02-09T02:54:15.083Z",
        "user_update_date": "2023-05-05T19:26:12.683Z",
        "user_cover": "cover URL",
        "user_phone": "0970111023",
        "user_intro": "user intro",
        "user_website": "website",
        "user_interests": [],
        "user_like": []
    },
    {
        "_id": "6481db2f77f0a16116c691c0",
        "user_name": "胡譽思",
        "user_email": "Tressie94@gmail.com",
        "user_hash_pwd": "$2a$12$klCk0uF5uQ2uFJ84EUa.q.CH5hzEsW.lXAveTxlhYV4xeffMZLvWS",
        "user_roles": [
            0
        ],
        "login_method": [
            0
        ],
        "oauth_google_id": "",
        "user_create_date": "2022-03-26T06:13:11.625Z",
        "user_update_date": "2023-05-16T07:43:38.104Z",
        "user_cover": "cover URL",
        "user_phone": "0954424846",
        "user_intro": "user intro",
        "user_website": "website",
        "user_interests": [],
        "user_like": []
    },
    {
        "_id": "6481db2f77f0a16116c691c1",
        "user_name": "景德廷",
        "user_email": "Summer96@yahoo.com",
        "user_hash_pwd": "$2a$12$aZ.1Z2AMGC//p9HWMNt7iO5po8d02VRiHoHz2sJv61fZS.iAbhKhm",
        "user_roles": [
            0
        ],
        "login_method": [
            0
        ],
        "oauth_google_id": "",
        "user_create_date": "2021-09-19T00:53:45.329Z",
        "user_update_date": "2023-05-07T20:22:32.243Z",
        "user_cover": "cover URL",
        "user_phone": "0929724351",
        "user_intro": "user intro",
        "user_website": "website",
        "user_interests": [],
        "user_like": []
    },
    {
        "_id": "6481db2f77f0a16116c691c2",
        "user_name": "曾源舒",
        "user_email": "Marian_Bahringer@hotmail.com",
        "user_hash_pwd": "$2a$12$gLWIYnM8AIuopPLM/9.uCukl7D7YcXk3XIFkEfFHa9RN5TIJnm16W",
        "user_roles": [
            0
        ],
        "login_method": [
            0
        ],
        "oauth_google_id": "",
        "user_create_date": "2022-04-27T09:37:48.589Z",
        "user_update_date": "2023-04-03T20:58:29.959Z",
        "user_cover": "cover URL",
        "user_phone": "0910440254",
        "user_intro": "user intro",
        "user_website": "website",
        "user_interests": [],
        "user_like": []
    },
    {
        "_id": "6481db2f77f0a16116c691c3",
        "user_name": "鄭慶筑",
        "user_email": "Rebeca23@hotmail.com",
        "user_hash_pwd": "$2a$12$BLiyzh0k/JI/hQptdzYA1.W.2sBKlkgEnoVBgtLbdBPreVcQH0Pny",
        "user_roles": [
            0
        ],
        "login_method": [
            0
        ],
        "oauth_google_id": "",
        "user_create_date": "2022-07-30T01:46:29.376Z",
        "user_update_date": "2023-05-12T16:53:57.239Z",
        "user_cover": "cover URL",
        "user_phone": "0933735665",
        "user_intro": "user intro",
        "user_website": "website",
        "user_interests": [],
        "user_like": []
    },
    {
        "_id": "6481db2f77f0a16116c691c4",
        "user_name": "郝勳瑩",
        "user_email": "Davion.Durgan@yahoo.com",
        "user_hash_pwd": "$2a$12$.PMPrnahsRUPqAbhXFArue/28CovzLmDVSIvBuBZtVPbDJwwq.D4i",
        "user_roles": [
            0
        ],
        "login_method": [
            0
        ],
        "oauth_google_id": "",
        "user_create_date": "2022-05-05T07:08:38.891Z",
        "user_update_date": "2023-04-18T03:47:22.276Z",
        "user_cover": "cover URL",
        "user_phone": "0912777818",
        "user_intro": "user intro",
        "user_website": "website",
        "user_interests": [],
        "user_like": []
    },
    {
        "_id": "6481db2f77f0a16116c691c5",
        "user_name": "上官寧雁",
        "user_email": "Kennedy11@gmail.com",
        "user_hash_pwd": "$2a$12$7EK9cAVegnn9dX1HUzCU.ewxdZOtdsP1dEuFujqErqCB.Q2qXI8My",
        "user_roles": [
            0
        ],
        "login_method": [
            0
        ],
        "oauth_google_id": "",
        "user_create_date": "2020-03-02T09:12:22.021Z",
        "user_update_date": "2023-04-08T17:40:01.188Z",
        "user_cover": "cover URL",
        "user_phone": "0938741703",
        "user_intro": "user intro",
        "user_website": "website",
        "user_interests": [],
        "user_like": []
    },
    {
        "_id": "6481db2f77f0a16116c691c6",
        "user_name": "朱樑明",
        "user_email": "Marlin_Pollich@hotmail.com",
        "user_hash_pwd": "$2a$12$Y.zWsZs3Yv4JB0SdW9bXOuZYJnbu0bDzWWQ2QNNcDLLp538z8LNFS",
        "user_roles": [
            0
        ],
        "login_method": [
            0
        ],
        "oauth_google_id": "",
        "user_create_date": "2021-10-01T22:45:33.458Z",
        "user_update_date": "2023-05-09T11:12:55.294Z",
        "user_cover": "cover URL",
        "user_phone": "0933080682",
        "user_intro": "user intro",
        "user_website": "website",
        "user_interests": [],
        "user_like": []
    },
    {
        "_id": "6481db2f77f0a16116c691c7",
        "user_name": "諸葛諭中",
        "user_email": "Aida.Adams43@gmail.com",
        "user_hash_pwd": "$2a$12$cJGZPrPYeFUskhuT9Zx/B.Xzr1sKD0Yh1Lnk0sfhtFcNi9BvZecvq",
        "user_roles": [
            0
        ],
        "login_method": [
            0
        ],
        "oauth_google_id": "",
        "user_create_date": "2022-07-31T19:12:45.367Z",
        "user_update_date": "2023-05-24T19:19:45.378Z",
        "user_cover": "cover URL",
        "user_phone": "0963687375",
        "user_intro": "user intro",
        "user_website": "website",
        "user_interests": [],
        "user_like": []
    },
    {
        "_id": "6481db2f77f0a16116c691c8",
        "user_name": "王翔文",
        "user_email": "Coy.Morissette@yahoo.com",
        "user_hash_pwd": "$2a$12$jBJBIggpEDnI6YoYcKkZJONkwZE.jLOZ2Q3sGGO90F/RPGAGcQ8rG",
        "user_roles": [
            0
        ],
        "login_method": [
            0
        ],
        "oauth_google_id": "",
        "user_create_date": "2021-11-26T02:27:06.472Z",
        "user_update_date": "2023-04-14T04:59:46.443Z",
        "user_cover": "cover URL",
        "user_phone": "0916766625",
        "user_intro": "user intro",
        "user_website": "website",
        "user_interests": [],
        "user_like": []
    },
    {
        "_id": "6481db2f77f0a16116c691c9",
        "user_name": "簡怡聖",
        "user_email": "Destiney92@hotmail.com",
        "user_hash_pwd": "$2a$12$HA3u6YfCywhr9Cs0AW.Khuv0XtaFdQXPKOBiB9OBTgN351DZxGm4C",
        "user_roles": [
            0
        ],
        "login_method": [
            0
        ],
        "oauth_google_id": "",
        "user_create_date": "2020-09-08T02:44:38.100Z",
        "user_update_date": "2023-04-11T11:06:25.751Z",
        "user_cover": "cover URL",
        "user_phone": "0955206110",
        "user_intro": "user intro",
        "user_website": "website",
        "user_interests": [],
        "user_like": []
    }
]